ayetms_cli/__init__.py
ayetms_cli/main.py
ayetms_cli_sau-0.1.2.dist-info/LICENSE
ayetms_cli_sau-0.1.2.dist-info/METADATA
ayetms_cli_sau-0.1.2.dist-info/WHEEL
ayetms_cli_sau-0.1.2.dist-info/entry_points.txt
ayetms_cli_sau-0.1.2.dist-info/top_level.txt
ayetms_cli_sau-0.1.2.dist-info/RECORD
