Metadata-Version: 2.1
Name: ayetms_cli_sau
Version: 0.1.2
Summary: A CLI app for AYETMS
Home-page: https://github.com/yourusername/ayetms-cli
Author: Saurabh Satapathy
Author-email: Saurabh Satapathy <saurabhsatapathy0@gmail.com>
Project-URL: Homepage, https://github.com/saurabh190802/ayetms_cli
Project-URL: Bug Tracker, https://github.com/saurabh190802/ayetms_cli/issues
Classifier: Programming Language :: Python :: 3
Classifier: License :: OSI Approved :: MIT License
Classifier: Operating System :: OS Independent
Requires-Python: >=3.6
License-File: LICENSE
